{
    "configurations": [
        {
            "name": "Win32",
            "includePath": [
                "${workspaceFolder}/**",
                "E:/eigen3/**",
                "${workspaceFolder}/include/eskf",
                "${workspaceFolder}/include/leskf",
                "${workspaceFolder}/include/geskf",
                "${workspaceFolder}/include/liekf",
                "${workspaceFolder}/include/riekf",
                "${workspaceFolder}/include/generator/**"
            ],
            "defines": [
                "_DEBUG",
                "UNICODE",
                "_UNICODE"
            ],
            "compilerPath": "E:\\mingw64\\bin\\gcc.exe",
            "cStandard": "gnu17",
            "cppStandard": "gnu++14",
            "intelliSenseMode": "windows-gcc-x64",
            "configurationProvider": "ms-vscode.cmake-tools"
        }
    ],
    "version": 4
}